# 写屏障

STAB 中写屏障主要是为了保证并行标记的正确性, STAB 主要记录的是目的对象修改之前的对象。

```java
public class Test {

    private Object obj;

    public Test() {
        obj = new Object();
    }
}
```

上面的 Java 代码反编译后的字节码: 

```
{
  public Test();
    descriptor: ()V
    flags: (0x0001) ACC_PUBLIC
    Code:
      stack=3, locals=1, args_size=1
         0: aload_0
         1: invokespecial #1                  // Method java/lang/Object."<init>":()V
         4: aload_0
         5: new           #2                  // class java/lang/Object
         8: dup
         9: invokespecial #1                  // Method java/lang/Object."<init>":()V
        12: putfield      #3                  // Field obj:Ljava/lang/Object;
        15: return
      LineNumberTable:
        line 7: 0
        line 8: 4
        line 9: 15
      LocalVariableTable:
        Start  Length  Slot  Name   Signature
            0      16     0  this   LTest;
}
```

其中的字段赋值会被翻译成 putfield 字节码指令。早期的 JVM 使用的是字节码解释器(BytecodeInterpreter), 后来使用模板解释器(TemplateTable)。它们的功能是一样的, 只不过实现的方式不同, 字节码解释器还需要再次解释执行到目标机器的代码, 而模板解释器是针对平台的, JVM 内部使用的是模板解释器, 它是汇编语言编写的。

## 字节码解释器

> jdk8u60-master\hotspot\src\share\vm\interpreter\bytecodeInterpreter.cpp

```cpp
CASE(_putfield):
CASE(_putstatic):
{
    // ...
    obj->obj_field_put(field_offset, STACK_OBJECT(-1));
    // ...
}
CASE(_new):
{
    // ...
}
```

> jdk8u60-master\hotspot\src\share\vm\oops\oop.inline.hpp

```cpp
inline void oopDesc::obj_field_put(int offset, oop value) {
  // UseCompressedOops表示是否开启了压缩指针
  UseCompressedOops ? oop_store(obj_field_addr<narrowOop>(offset), value) :
                      oop_store(obj_field_addr<oop>(offset),       value);
}

template <class T> inline void oop_store(volatile T* p, oop v) {
  // 写前屏障
  update_barrier_set_pre((T*)p, v);
  // 赋值
  oopDesc::release_encode_store_heap_oop(p, v);
  // 写后屏障
  update_barrier_set((void*)p, v, true);
}

template <class T> inline void update_barrier_set_pre(T* p, oop v) {
  oopDesc::bs()->write_ref_field_pre(p, v);
}

inline void update_barrier_set(void* p, oop v, bool release = false) {
  oopDesc::bs()->write_ref_field(p, v, release);
}
```

写前屏障会调用到 G1SATBCardTableModRefBS::inline_write_ref_field_pre()方法。

> jdk8u60-master\hotspot\src\share\vm\gc_implementation\g1\g1SATBCardTableModRefBS.hpp

```cpp
class G1SATBCardTableModRefBS: public CardTableModRefBSForCTRS {
public:
  template <class T> inline void inline_write_ref_field_pre(T* field, oop newVal) {
    write_ref_field_pre_static(field, newVal);
  }

  template <class T> static void write_ref_field_pre_static(T* field, oop newVal) {
    T heap_oop = oopDesc::load_heap_oop(field);
    if (!oopDesc::is_null(heap_oop)) {
      enqueue(oopDesc::decode_heap_oop(heap_oop));
    }
  }
}
```

> jdk8u60-master\hotspot\src\share\vm\gc_implementation\g1\g1SATBCardTableModRefBS.cpp

```cpp
void G1SATBCardTableModRefBS::enqueue(oop pre_val) {
  if (!JavaThread::satb_mark_queue_set().is_active()) {
    return;
  }
  Thread* thr = Thread::current();
  if (thr->is_Java_thread()) {
    // 放到Java线程的satb队列中
    JavaThread* jt = (JavaThread*)thr;
    jt->satb_mark_queue().enqueue(pre_val);
  } else {
    // 对于本地代码, 则放入到全局的satb队列中
    MutexLockerEx x(Shared_SATB_Q_lock, Mutex::_no_safepoint_check_flag);
    JavaThread::satb_mark_queue_set().shared_satb_queue()->enqueue(pre_val);
  }
}
```

写后屏障会调用到 G1SATBCardTableLoggingModRefBS::write_ref_field_work()方法。

> jdk8u60-master\hotspot\src\share\vm\gc_implementation\g1\g1SATBCardTableModRefBS.cpp

```cpp
/**
 * 对于Java中的赋值语句: obj = new Object();
 * field 是 obj
 * new_val 是 new Object()
 */
void G1SATBCardTableLoggingModRefBS::write_ref_field_work(void* field,
                                                          oop new_val,
                                                          bool release) {
  // 获取字段所在的对象对应的card
  volatile jbyte* byte = byte_for(field);
  // 不处理新生代的card, 因为新生代一定会被在CSet中
  if (*byte == g1_young_gen) {
    return;
  }
  // StoreLoad屏障, 保证数据的可见性
  OrderAccess::storeload();
  if (*byte != dirty_card) {
    // 将card设置为dirty
    *byte = dirty_card;
    Thread* thr = Thread::current();
    if (thr->is_Java_thread()) {
    // 放到Java线程的DCQ中
      JavaThread* jt = (JavaThread*)thr;
      jt->dirty_card_queue().enqueue(byte);
    } else {
    // 对于本地代码, 则放入到全局的DCQ中
      MutexLockerEx x(Shared_DirtyCardQ_lock,
                      Mutex::_no_safepoint_check_flag);
      _dcqs.shared_dirty_card_queue()->enqueue(byte);
    }
  }
}
```

## 模板解释器

对于模板解释器, putfield 会调用 putfield_or_static()方法。

> jdk8u60-master\hotspot\src\cpu\x86\vm\templateTable_x86_32.cpp

```cpp
void TemplateTable::putfield_or_static(int byte_no, bool is_static) {
  {
    // __ 是汇编器的别名, 根据不同的系统会调用不同的汇编器
    __ pop(atos);
    if (!is_static) pop_and_check_object(obj);
    do_oop_store(_masm, lo, rax, _bs->kind(), false);
    if (!is_static) {
      patch_bytecode(Bytecodes::_fast_aputfield, rcx, rbx, true, byte_no);
    }
    __ jmp(Done);
  }
}

static void do_oop_store(InterpreterMacroAssembler* _masm,
                         Address obj,
                         Register val,
                         BarrierSet::Name barrier,
                         bool precise) {
  switch (barrier) {
#if INCLUDE_ALL_GCS
    case BarrierSet::G1SATBCT:
    case BarrierSet::G1SATBCTLogging:
      {
        if (obj.index() == noreg && obj.disp() == 0) {
          if (obj.base() != rdx) {
            __ movl(rdx, obj.base());
          }
        } else {
          __ leal(rdx, obj);
        }
        __ get_thread(rcx);
        __ save_bcp();
        // 写前屏障, 处理satb
        __ g1_write_barrier_pre(rdx, rbx, rcx, rsi, val != noreg, false);

        if (val == noreg) {
          // 赋值空对象, 不需要处理dcq
          __ movptr(Address(rdx, 0), NULL_WORD);
        } else {
          // 赋值
          __ movl(Address(rdx, 0), val);
          // 写后屏障, 处理dcq
          __ g1_write_barrier_post(rdx, val, rcx, rbx, rsi);
        }
        __ restore_bcp();

      }
      break;
#endif
    // ...
  }
}
```
